cruscopoetry/core/__init__.py
cruscopoetry/core/__main__.py
cruscopoetry/core/base_parser.py
cruscopoetry/core/cmdline.py
cruscopoetry/core/exceptions.py
cruscopoetry/core/markers.py
cruscopoetry/core/jsonparser/__init__.py
cruscopoetry/core/jsonparser/exceptions.py
cruscopoetry/core/jsonparser/joiners.py
cruscopoetry/core/jsonparser/json_parser.py
cruscopoetry/core/jsonparser/metadata_parser.py
cruscopoetry/core/jsonparser/notes_parser.py
cruscopoetry/core/jsonparser/text_element.py
cruscopoetry/core/jsonparser/text_parser.py
cruscopoetry/core/jsonparser/translations.py
cruscopoetry/core/jsonparser/utils.py
cruscopoetry/core/poemparser/__init__.py
cruscopoetry/core/poemparser/poem_parser.py
cruscopoetry/core/poemparser/utils.py
cruscopoetry/core/poemparser/metadataparser/__init__.py
cruscopoetry/core/poemparser/metadataparser/exceptions.py
cruscopoetry/core/poemparser/metadataparser/metadata_parser.py
cruscopoetry/core/poemparser/notesparser/__init__.py
cruscopoetry/core/poemparser/notesparser/notes_parser.py
cruscopoetry/core/poemparser/textparser/__init__.py
cruscopoetry/core/poemparser/textparser/exceptions.py
cruscopoetry/core/poemparser/textparser/syntax_handlers.py
cruscopoetry/core/poemparser/textparser/text_parser.py
cruscopoetry/core/project/__init__.py
cruscopoetry/core/project/exceptions.py
cruscopoetry/core/project/project_manager.py
cruscopoetry/core/project/resources_browser.py
cruscopoetry/core/renderers/__init__.py
cruscopoetry/core/renderers/abstract_renderer.py
cruscopoetry/core/renderers/exceptions.py
cruscopoetry/core/renderers/abstractrenderer/__init__.py
cruscopoetry/core/renderers/abstractrenderer/abstract_disposers.py
cruscopoetry/core/renderers/abstractrenderer/abstract_line_renderer.py
cruscopoetry/core/renderers/abstractrenderer/abstract_metadata_renderer.py
cruscopoetry/core/renderers/abstractrenderer/abstract_notes_renderer.py
cruscopoetry/core/renderers/abstractrenderer/abstract_renderer.py
cruscopoetry.core-0.0.3.dist-info/METADATA
cruscopoetry.core-0.0.3.dist-info/WHEEL
cruscopoetry.core-0.0.3.dist-info/entry_points.txt
cruscopoetry.core-0.0.3.dist-info/top_level.txt
cruscopoetry.core-0.0.3.dist-info/RECORD
