Metadata-Version: 2.1
Name: cruscopoetry.core
Version: 0.0.3
Summary: Parser for poems in CruscoPoetry format
Home-page: https://gitlab.com/kikulacho92/cruscopoetry_new
Author: Emiliano Minerba
Author-email: emi.nerba@gmail.com
License: GPL
Platform: UNKNOWN
Requires-Dist: myusefulclasses
Requires-Dist: myusefulmetaclasses
Requires-Dist: pycountry==22.3.5
Requires-Dist: wheel
